pytest_mongo/__init__.py
pytest_mongo/config.py
pytest_mongo/executor_noop.py
pytest_mongo/factories.py
pytest_mongo/plugin.py
pytest_mongo/py.typed
pytest_mongo-3.2.1.dist-info/licenses/AUTHORS.rst
pytest_mongo-3.2.1.dist-info/licenses/LICENSE
pytest_mongo-3.2.1.dist-info/METADATA
pytest_mongo-3.2.1.dist-info/WHEEL
pytest_mongo-3.2.1.dist-info/entry_points.txt
pytest_mongo-3.2.1.dist-info/top_level.txt
pytest_mongo-3.2.1.dist-info/zip-safe
pytest_mongo-3.2.1.dist-info/RECORD
